odoo9_addon_mrp_mto_with_stock-9.0.1.0.0.99.dev8-py3.8-nspkg.pth
odoo_addons/mrp_mto_with_stock/README.rst
odoo_addons/mrp_mto_with_stock/__init__.py
odoo_addons/mrp_mto_with_stock/__openerp__.py
odoo_addons/mrp_mto_with_stock/i18n/ca.po
odoo_addons/mrp_mto_with_stock/i18n/de.po
odoo_addons/mrp_mto_with_stock/i18n/en_US.po
odoo_addons/mrp_mto_with_stock/i18n/es.po
odoo_addons/mrp_mto_with_stock/i18n/es_MX.po
odoo_addons/mrp_mto_with_stock/i18n/fi.po
odoo_addons/mrp_mto_with_stock/i18n/fr.po
odoo_addons/mrp_mto_with_stock/i18n/fr_CH.po
odoo_addons/mrp_mto_with_stock/i18n/gl.po
odoo_addons/mrp_mto_with_stock/i18n/hr.po
odoo_addons/mrp_mto_with_stock/i18n/hr_HR.po
odoo_addons/mrp_mto_with_stock/i18n/it.po
odoo_addons/mrp_mto_with_stock/i18n/mrp_mto_with_stock.pot
odoo_addons/mrp_mto_with_stock/i18n/pt_BR.po
odoo_addons/mrp_mto_with_stock/i18n/ro.po
odoo_addons/mrp_mto_with_stock/i18n/sl.po
odoo_addons/mrp_mto_with_stock/i18n/tr.po
odoo_addons/mrp_mto_with_stock/i18n/tr_TR.po
odoo_addons/mrp_mto_with_stock/i18n/vi_VN.po
odoo_addons/mrp_mto_with_stock/i18n/zh_CN.po
odoo_addons/mrp_mto_with_stock/models/__init__.py
odoo_addons/mrp_mto_with_stock/models/mrp_production.py
odoo_addons/mrp_mto_with_stock/models/product_template.py
odoo_addons/mrp_mto_with_stock/static/description/icon.png
odoo_addons/mrp_mto_with_stock/tests/__init__.py
odoo_addons/mrp_mto_with_stock/tests/test_mrp_mto_with_stock.py
odoo_addons/mrp_mto_with_stock/views/mrp_production_view.xml
odoo_addons/mrp_mto_with_stock/views/product_template_view.xml
odoo9_addon_mrp_mto_with_stock-9.0.1.0.0.99.dev8.dist-info/METADATA
odoo9_addon_mrp_mto_with_stock-9.0.1.0.0.99.dev8.dist-info/WHEEL
odoo9_addon_mrp_mto_with_stock-9.0.1.0.0.99.dev8.dist-info/namespace_packages.txt
odoo9_addon_mrp_mto_with_stock-9.0.1.0.0.99.dev8.dist-info/top_level.txt
odoo9_addon_mrp_mto_with_stock-9.0.1.0.0.99.dev8.dist-info/RECORD
