Metadata-Version: 2.1
Name: odoo9-addon-mrp-mto-with-stock
Version: 9.0.1.0.0.99.dev8
Summary: Fix Manufacturing orders to pull from stock until qty is zero, and then create a procurement for them.
Home-page: https://odoo-community.org/
Author: John Walsh, Eficent, Odoo Community Association (OCA)
Author-email: support@odoo-community.org
License: AGPL-3
Platform: UNKNOWN
Classifier: Programming Language :: Python
Classifier: Framework :: Odoo
Classifier: Framework :: Odoo :: 9.0
Classifier: License :: OSI Approved :: GNU Affero General Public License v3
Requires-Python: ~=2.7
Requires-Dist: odoo (<9.1a,>=9.0a)
